pspso/__init__.py
pspso/pspso.py
pspso-0.1.3.dist-info/LICENSE.txt
pspso-0.1.3.dist-info/METADATA
pspso-0.1.3.dist-info/WHEEL
pspso-0.1.3.dist-info/top_level.txt
pspso-0.1.3.dist-info/RECORD
