Metadata-Version: 2.1
Name: pspso
Version: 0.1.3
Summary: pspso is a python package for selecting machine learning algorithms parameters.
Home-page: https://github.com/ayhaidar/pspso
Author: Ali Haidar
Author-email: ali.hdrv@outlook.com
License: MIT
Platform: UNKNOWN
Classifier: Development Status :: 4 - Beta
Classifier: License :: OSI Approved :: MIT License
Classifier: Programming Language :: Python
Classifier: Programming Language :: Python :: 3.5
Classifier: Programming Language :: Python :: 3.6
Classifier: Topic :: Software Development :: Libraries
Classifier: Topic :: Software Development :: Libraries :: Python Modules
Classifier: Intended Audience :: Developers
Requires-Python: >=3.5
Requires-Dist: numpy (==1.16.1)
Requires-Dist: lightgbm
Requires-Dist: xgboost
Requires-Dist: scikit-learn (>=0.21.2)
Requires-Dist: keras
Requires-Dist: tensorflow
Requires-Dist: pyswarms (>=1.0.2)
Requires-Dist: matplotlib (>=3.1.1)
